{"nodes":[{"id":"ckm_ui_styling_skill","label":"CKM UI Styling Skill","file_type":"concept","source_file":".agents/skills/ckm-ui-styling/SKILL.md","source_location":null,"source_url":null,"captured_at":null,"author":null,"contributor":null},{"id":"canvas_fonts_silkscreen","label":"Silkscreen Font (OFL)","file_type":"concept","source_file":".agents/skills/ckm-ui-styling/canvas-fonts/Silkscreen-OFL.txt","source_location":null,"source_url":null,"captured_at":null,"author":null,"contributor":null},{"id":"canvas_fonts_worksans","label":"Work Sans Font (OFL)","file_type":"concept","source_file":".agents/skills/ckm-ui-styling/canvas-fonts/WorkSans-OFL.txt","source_location":null,"source_url":null,"captured_at":null,"author":null,"contributor":null},{"id":"canvas_fonts_lora","label":"Lora Font (OFL)","file_type":"concept","source_file":".agents/skills/ckm-ui-styling/canvas-fonts/Lora-OFL.txt","source_location":null,"source_url":null,"captured_at":null,"author":null,"contributor":null},{"id":"canvas_fonts_instrumentsans","label":"Instrument Sans Font (OFL)","file_type":"concept","source_file":".agents/skills/ckm-ui-styling/canvas-fonts/InstrumentSans-OFL.txt","source_location":null,"source_url":null,"captured_at":null,"author":null,"contributor":null},{"id":"canvas_fonts_jetbrainsmono","label":"JetBrains Mono Font (OFL)","file_type":"concept","source_file":".agents/skills/ckm-ui-styling/canvas-fonts/JetBrainsMono-OFL.txt","source_location":null,"source_url":null,"captured_at":null,"author":null,"contributor":null},{"id":"canvas_fonts_geistmono","label":"Geist Mono Font (OFL)","file_type":"concept","source_file":".agents/skills/ckm-ui-styling/canvas-fonts/GeistMono-OFL.txt","source_location":null,"source_url":null,"captured_at":null,"author":null,"contributor":null},{"id":"canvas_fonts_ibmplexmono","label":"IBM Plex Mono Font (OFL)","file_type":"concept","source_file":".agents/skills/ckm-ui-styling/canvas-fonts/IBMPlexMono-OFL.txt","source_location":null,"source_url":null,"captured_at":null,"author":null,"contributor":null},{"id":"references_shadcn_theming","label":"Shadcn Theming Reference","file_type":"document","source_file":".agents/skills/ckm-ui-styling/references/shadcn-theming.md","source_location":null,"source_url":null,"captured_at":null,"author":null,"contributor":null},{"id":"references_tailwind_utilities","label":"Tailwind Utilities Reference","file_type":"document","source_file":".agents/skills/ckm-ui-styling/references/tailwind-utilities.md","source_location":null,"source_url":null,"captured_at":null,"author":null,"contributor":null},{"id":"references_tailwind_responsive","label":"Tailwind Responsive Reference","file_type":"document","source_file":".agents/skills/ckm-ui-styling/references/tailwind-responsive.md","source_location":null,"source_url":null,"captured_at":null,"author":null,"contributor":null},{"id":"concept_sil_ofl_license","label":"SIL Open Font License 1.1","file_type":"concept","source_file":".agents/skills/ckm-ui-styling/canvas-fonts/Silkscreen-OFL.txt","source_location":null,"source_url":null,"captured_at":null,"author":null,"contributor":null},{"id":"concept_css_variables","label":"CSS Custom Properties / Variables","file_type":"concept","source_file":".agents/skills/ckm-ui-styling/references/shadcn-theming.md","source_location":null,"source_url":null,"captured_at":null,"author":null,"contributor":null},{"id":"concept_tailwind_breakpoints","label":"Tailwind CSS Breakpoints","file_type":"concept","source_file":".agents/skills/ckm-ui-styling/references/tailwind-responsive.md","source_location":null,"source_url":null,"captured_at":null,"author":null,"contributor":null}],"edges":[{"source":"canvas_fonts_silkscreen","target":"concept_sil_ofl_license","relation":"references","confidence":"EXTRACTED","confidence_score":1.0,"source_file":".agents/skills/ckm-ui-styling/canvas-fonts/Silkscreen-OFL.txt","source_location":null,"weight":1.0},{"source":"canvas_fonts_worksans","target":"concept_sil_ofl_license","relation":"references","confidence":"EXTRACTED","confidence_score":1.0,"source_file":".agents/skills/ckm-ui-styling/canvas-fonts/WorkSans-OFL.txt","source_location":null,"weight":1.0},{"source":"canvas_fonts_jetbrainsmono","target":"concept_sil_ofl_license","relation":"references","confidence":"EXTRACTED","confidence_score":1.0,"source_file":".agents/skills/ckm-ui-styling/canvas-fonts/JetBrainsMono-OFL.txt","source_location":null,"weight":1.0},{"source":"references_shadcn_theming","target":"concept_css_variables","relation":"references","confidence":"EXTRACTED","confidence_score":1.0,"source_file":".agents/skills/ckm-ui-styling/references/shadcn-theming.md","source_location":null,"weight":1.0},{"source":"references_tailwind_responsive","target":"concept_tailwind_breakpoints","relation":"references","confidence":"EXTRACTED","confidence_score":1.0,"source_file":".agents/skills/ckm-ui-styling/references/tailwind-responsive.md","source_location":null,"weight":1.0},{"source":"ckm_ui_styling_skill","target":"references_shadcn_theming","relation":"references","confidence":"INFERRED","confidence_score":0.95,"source_file":".agents/skills/ckm-ui-styling/SKILL.md","source_location":null,"weight":1.0},{"source":"ckm_ui_styling_skill","target":"references_tailwind_utilities","relation":"references","confidence":"INFERRED","confidence_score":0.95,"source_file":".agents/skills/ckm-ui-styling/SKILL.md","source_location":null,"weight":1.0}],"hyperedges":[],"input_tokens":0,"output_tokens":0}
